langextract/__init__.py
langextract/annotation.py
langextract/chunking.py
langextract/data.py
langextract/data_lib.py
langextract/exceptions.py
langextract/extraction.py
langextract/factory.py
langextract/inference.py
langextract/io.py
langextract/plugins.py
langextract/progress.py
langextract/prompt_validation.py
langextract/prompting.py
langextract/py.typed
langextract/registry.py
langextract/resolver.py
langextract/schema.py
langextract/tokenizer.py
langextract/visualization.py
langextract/_compat/__init__.py
langextract/_compat/exceptions.py
langextract/_compat/inference.py
langextract/_compat/registry.py
langextract/_compat/schema.py
langextract/core/__init__.py
langextract/core/base_model.py
langextract/core/data.py
langextract/core/debug_utils.py
langextract/core/exceptions.py
langextract/core/format_handler.py
langextract/core/schema.py
langextract/core/tokenizer.py
langextract/core/types.py
langextract/providers/__init__.py
langextract/providers/builtin_registry.py
langextract/providers/gemini.py
langextract/providers/gemini_batch.py
langextract/providers/ollama.py
langextract/providers/openai.py
langextract/providers/patterns.py
langextract/providers/router.py
langextract/providers/schemas/__init__.py
langextract/providers/schemas/gemini.py
langextract-1.1.0.dist-info/licenses/LICENSE
langextract-1.1.0.dist-info/METADATA
langextract-1.1.0.dist-info/WHEEL
langextract-1.1.0.dist-info/entry_points.txt
langextract-1.1.0.dist-info/top_level.txt
langextract-1.1.0.dist-info/RECORD
