Metadata-Version: 2.4
Name: langextract
Version: 1.1.0
Summary: LangExtract: A library for extracting structured data from language models
Author-email: Akshay Goel <goelak@google.com>
License-Expression: Apache-2.0
Project-URL: Homepage, https://github.com/google/langextract
Project-URL: Repository, https://github.com/google/langextract
Project-URL: Documentation, https://github.com/google/langextract/blob/main/README.md
Project-URL: Bug Tracker, https://github.com/google/langextract/issues
Project-URL: Changelog, https://github.com/google/langextract/releases
Project-URL: DOI, https://doi.org/10.5281/zenodo.17015089
Requires-Python: >=3.10
License-File: LICENSE
Requires-Dist: absl-py>=1.0.0
Requires-Dist: aiohttp>=3.8.0
Requires-Dist: async_timeout>=4.0.0
Requires-Dist: exceptiongroup>=1.1.0
Requires-Dist: google-genai>=1.39.0
Requires-Dist: google-cloud-storage>=2.14.0
Requires-Dist: ml-collections>=0.1.0
Requires-Dist: more-itertools>=8.0.0
Requires-Dist: numpy>=1.20.0
Requires-Dist: pandas>=1.3.0
Requires-Dist: pydantic>=1.8.0
Requires-Dist: python-dotenv>=0.19.0
Requires-Dist: PyYAML>=6.0
Requires-Dist: requests>=2.25.0
Requires-Dist: tqdm>=4.64.0
Requires-Dist: typing-extensions>=4.0.0
Provides-Extra: openai
Requires-Dist: openai>=1.50.0; extra == "openai"
Provides-Extra: all
Requires-Dist: openai>=1.50.0; extra == "all"
Provides-Extra: dev
Requires-Dist: pyink~=24.3.0; extra == "dev"
Requires-Dist: isort>=5.13.0; extra == "dev"
Requires-Dist: pylint>=3.0.0; extra == "dev"
Requires-Dist: pytype>=2024.10.11; extra == "dev"
Requires-Dist: tox>=4.0.0; extra == "dev"
Requires-Dist: import-linter>=2.0; extra == "dev"
Provides-Extra: test
Requires-Dist: pytest>=7.4.0; extra == "test"
Requires-Dist: tomli>=2.0.0; extra == "test"
Provides-Extra: notebook
Requires-Dist: ipython>=7.0.0; extra == "notebook"
Requires-Dist: notebook>=6.0.0; extra == "notebook"
Dynamic: license-file
